odoo8_addon_web_context_tunnel-8.0.2.0.0-py2.7-nspkg.pth
odoo_addons/web_context_tunnel/__openerp__.py
odoo_addons/web_context_tunnel/__init__.py
odoo_addons/web_context_tunnel/i18n/web_context_tunnel.pot
odoo_addons/web_context_tunnel/views/web_context_tunnel.xml
odoo_addons/web_context_tunnel/static/description/icon.png
odoo_addons/web_context_tunnel/static/test/context_tunnel.js
odoo_addons/web_context_tunnel/static/src/js/context_tunnel.js
odoo8_addon_web_context_tunnel-8.0.2.0.0.dist-info/top_level.txt
odoo8_addon_web_context_tunnel-8.0.2.0.0.dist-info/WHEEL
odoo8_addon_web_context_tunnel-8.0.2.0.0.dist-info/RECORD
odoo8_addon_web_context_tunnel-8.0.2.0.0.dist-info/metadata.json
odoo8_addon_web_context_tunnel-8.0.2.0.0.dist-info/DESCRIPTION.rst
odoo8_addon_web_context_tunnel-8.0.2.0.0.dist-info/METADATA
odoo8_addon_web_context_tunnel-8.0.2.0.0.dist-info/namespace_packages.txt
